huntglitch_python/__init__.py
huntglitch_python/config.py
huntglitch_python/logger.py
huntglitch_python-1.2.0.dist-info/licenses/LICENSE
huntglitch_python-1.2.0.dist-info/METADATA
huntglitch_python-1.2.0.dist-info/WHEEL
huntglitch_python-1.2.0.dist-info/top_level.txt
huntglitch_python-1.2.0.dist-info/RECORD
