Metadata-Version: 2.4
Name: huntglitch-python
Version: 1.2.0
Summary: Send Python exceptions and logs to HuntGlitch
Home-page: https://github.com/huntglitch-npm/huntglitch-python
Author: HuntGlitch
Author-email: HuntGlitch <support@huntglitch.com>
Maintainer-email: HuntGlitch <support@huntglitch.com>
License: MIT
Project-URL: Homepage, https://github.com/huntglitch-npm/huntglitch-python
Project-URL: Documentation, https://github.com/huntglitch-npm/huntglitch-python#readme
Project-URL: Repository, https://github.com/huntglitch-npm/huntglitch-python.git
Project-URL: Bug Tracker, https://github.com/huntglitch-npm/huntglitch-python/issues
Keywords: logging,error tracking,monitoring,debugging,huntglitch
Classifier: Development Status :: 5 - Production/Stable
Classifier: Intended Audience :: Developers
Classifier: Topic :: Software Development :: Libraries :: Python Modules
Classifier: Topic :: System :: Logging
Classifier: Topic :: System :: Monitoring
Classifier: License :: OSI Approved :: MIT License
Classifier: Programming Language :: Python :: 3
Classifier: Programming Language :: Python :: 3.7
Classifier: Programming Language :: Python :: 3.8
Classifier: Programming Language :: Python :: 3.9
Classifier: Programming Language :: Python :: 3.10
Classifier: Programming Language :: Python :: 3.11
Classifier: Programming Language :: Python :: 3.12
Requires-Python: >=3.7
License-File: LICENSE
Requires-Dist: requests<3.0.0,>=2.25.0
Provides-Extra: env
Requires-Dist: python-dotenv<2.0.0,>=0.19.0; extra == "env"
Provides-Extra: dev
Requires-Dist: pytest>=6.0.0; extra == "dev"
Requires-Dist: pytest-cov>=2.0.0; extra == "dev"
Requires-Dist: black>=21.0.0; extra == "dev"
Requires-Dist: flake8>=3.8.0; extra == "dev"
Requires-Dist: mypy>=0.910; extra == "dev"
Dynamic: author
Dynamic: home-page
Dynamic: license-file
Dynamic: requires-python
